pptx_tools/__init__.py
pptx_tools/better_abc.py
pptx_tools/creator.py
pptx_tools/enumerations.py
pptx_tools/fill_style.py
pptx_tools/font_style.py
pptx_tools/paragraph_style.py
pptx_tools/position.py
pptx_tools/style_sheets.py
pptx_tools/table_style.py
pptx_tools/templates.py
pptx_tools/utils.py
pptx_tools/examples/__init__.py
pptx_tools/examples/font_style_example_01.py
pptx_tools/examples/general_example_01.py
pptx_tools/examples/paragraph_style_example_01.py
pptx_tools/examples/table_style_example_01.py
pptx_tools/examples/output/font_style_example_01.pptx
pptx_tools/examples/output/general_example_01.pdf
pptx_tools/examples/output/general_example_01.pptx
pptx_tools/examples/output/general_example_01_pngs/Folie1.PNG
pptx_tools/examples/output/general_example_01_pngs/Folie2.PNG
pptx_tools/examples/output/general_example_01_pngs/Folie3.PNG
pptx_tools/examples/output/general_example_01_pngs/Folie4.PNG
pptx_tools/examples/output/general_example_01_pngs/Folie5.PNG
pptx_tools/resources/example-template.pptx
python_pptx_interface-0.0.14.dist-info/METADATA
python_pptx_interface-0.0.14.dist-info/WHEEL
python_pptx_interface-0.0.14.dist-info/licenses/LICENSE
python_pptx_interface-0.0.14.dist-info/RECORD
