Metadata-Version: 2.4
Name: python-pptx-interface
Version: 0.0.14
Summary: Easy interface to create pptx-files using python-pptx
Project-URL: Homepage, https://github.com/natter1/python_pptx_interface
Project-URL: Issues, https://github.com/natter1/python_pptx_interface/issues
Author: Nathanael Jöhrmann
License-Expression: MIT
License-File: LICENSE
Classifier: Operating System :: OS Independent
Classifier: Programming Language :: Python :: 3
Requires-Python: >=3.9
Requires-Dist: comtypes>=1.4.10
Requires-Dist: matplotlib>=3.9.2
Requires-Dist: python-pptx>=1.0.0
Requires-Dist: scipy>=1.8.0
Provides-Extra: dev
Requires-Dist: pytest>=8.3.5; extra == 'dev'
